maluforce/__init__.py
maluforce/__version__.py
maluforce/core.py
maluforce/fileutils.py
maluforce/reportutils.py
maluforce/validators.py
maluforce-1.0.2.dist-info/LICENSE.txt
maluforce-1.0.2.dist-info/METADATA
maluforce-1.0.2.dist-info/WHEEL
maluforce-1.0.2.dist-info/top_level.txt
maluforce-1.0.2.dist-info/RECORD
