Metadata-Version: 2.1
Name: maluforce
Version: 1.0.2
Summary: A basic Salesforce and Pandas interface
Home-page: https://github.com/rodrigoelemesmo/maluforce
Author: Rodrigo Maluf
Author-email: rodrigo1793@gmail.com
Maintainer: Rodrigo Maluf
Maintainer-email: rodrigo1793@gmail.com
License: None
Keywords: python salesforce salesforce.com pandas
Platform: UNKNOWN
Classifier: Development Status :: 4 - Beta
Classifier: License :: OSI Approved :: Apache Software License
Classifier: Intended Audience :: Developers
Classifier: Intended Audience :: System Administrators
Classifier: Operating System :: OS Independent
Classifier: Topic :: Internet :: WWW/HTTP
Classifier: Programming Language :: Python :: 3.5
Classifier: Programming Language :: Python :: 3.6
Classifier: Programming Language :: Python :: 3.7
Classifier: Programming Language :: Python :: 3.8
Classifier: Programming Language :: Python :: Implementation :: PyPy
Requires-Dist: pandas
Requires-Dist: numpy (==1.16.4)
Requires-Dist: simple-salesforce (>=1.0.0)
